pytorch_transformers/__init__.py
pytorch_transformers/__main__.py
pytorch_transformers/convert_gpt2_checkpoint_to_pytorch.py
pytorch_transformers/convert_openai_checkpoint_to_pytorch.py
pytorch_transformers/convert_pytorch_checkpoint_to_tf.py
pytorch_transformers/convert_roberta_checkpoint_to_pytorch.py
pytorch_transformers/convert_tf_checkpoint_to_pytorch.py
pytorch_transformers/convert_transfo_xl_checkpoint_to_pytorch.py
pytorch_transformers/convert_xlm_checkpoint_to_pytorch.py
pytorch_transformers/convert_xlnet_checkpoint_to_pytorch.py
pytorch_transformers/file_utils.py
pytorch_transformers/modeling_auto.py
pytorch_transformers/modeling_bert.py
pytorch_transformers/modeling_gpt2.py
pytorch_transformers/modeling_openai.py
pytorch_transformers/modeling_roberta.py
pytorch_transformers/modeling_transfo_xl.py
pytorch_transformers/modeling_transfo_xl_utilities.py
pytorch_transformers/modeling_utils.py
pytorch_transformers/modeling_xlm.py
pytorch_transformers/modeling_xlnet.py
pytorch_transformers/optimization.py
pytorch_transformers/tokenization_auto.py
pytorch_transformers/tokenization_bert.py
pytorch_transformers/tokenization_gpt2.py
pytorch_transformers/tokenization_openai.py
pytorch_transformers/tokenization_roberta.py
pytorch_transformers/tokenization_transfo_xl.py
pytorch_transformers/tokenization_utils.py
pytorch_transformers/tokenization_xlm.py
pytorch_transformers/tokenization_xlnet.py
pytorch_transformers-1.1.0.dist-info/LICENSE
pytorch_transformers-1.1.0.dist-info/METADATA
pytorch_transformers-1.1.0.dist-info/WHEEL
pytorch_transformers-1.1.0.dist-info/entry_points.txt
pytorch_transformers-1.1.0.dist-info/top_level.txt
pytorch_transformers-1.1.0.dist-info/RECORD
