Metadata-Version: 2.1
Name: pytorch_transformers
Version: 1.1.0
Summary: Repository of pre-trained NLP Transformer models: BERT & RoBERTa, GPT & GPT-2, Transformer-XL, XLNet and XLM
Home-page: https://github.com/huggingface/pytorch-transformers
Author: Thomas Wolf, Lysandre Debut, Victor Sanh, Julien Chaumond, Google AI Language Team Authors, Open AI team Authors
Author-email: thomas@huggingface.co
License: Apache
Keywords: NLP deep learning transformer pytorch BERT GPT GPT-2 google openai CMU
Platform: UNKNOWN
Classifier: Intended Audience :: Science/Research
Classifier: License :: OSI Approved :: Apache Software License
Classifier: Programming Language :: Python :: 3
Classifier: Topic :: Scientific/Engineering :: Artificial Intelligence
